  <db type="fromQuery">
    <dbRecord>
      <key>
        root
      </key>
      <value>
        <name>
          Himanshu
        </name>
        <description>
          Root for the Repo
        </description>
        <children>
        </children>
        <payload>
          <value>
            ../root
          </value>
          <namespace>
          </namespace>
          <status>
            2
          </status>
          <categories>
			  <category>
              Administrator
            </category>
          </categories>
        </payload>
      </value>
    </dbRecord>
    <dbRecord>
      <key>
        ::namespace1::namespace2::file1.cpp.1
      </key>
      <value>
        <name>
          Himanshu
        </name>
        <description>
          file1.cpp file
        </description>
        <children>
          <child>
            ::namespace1::namespace2::file1.h.1
          </child>
        </children>
        <payload>
          <value>
            ../root/namespace1/namespace2/file1.cpp.1
          </value>
          <namespace>
            ::namespace1::namespace2::
          </namespace>
          <status>
            0
          </status>
          <categories>
			  <category>
              Cat1
            </category>
            <category>
              Cat2
            </category>
          </categories>
        </payload>
      </value>
    </dbRecord>
    <dbRecord>
      <key>
        ::namespace1::namespace2::file1.h.1
      </key>
      <value>
        <name>
          Himanshu
        </name>
        <description>
          file1.h file
        </description>
        <children>
        </children>
        <payload>
          <value>
            ../root/namespace1/namespace2/file1.h.1
          </value>
          <namespace>
            ::namespace1::namespace2::
          </namespace>
          <status>
            2
          </status>
          <categories>
			     <category>
              Cat1
            </category>
            <category>
              Cat2
            </category>
          </categories>
        </payload>
      </value>
    </dbRecord>
    <dbRecord>
      <key>
        ::namespace3::file2.cpp.1
      </key>
      <value>
        <name>
          Himanshu
        </name>
        <description>
          file2.cpp file
        </description>
        <children>
          <child>
            ::namespace3::file2.h.1
          </child>
        </children>
        <payload>
          <value>
            ../root/namespace3/file2.cpp.1
          </value>
          <namespace>
            ::namespace3::
          </namespace>
          <status>
            2
          </status>
          <categories>
			  <category>
              Cat3
            </category>
            <category>
              Cat4
            </category>
          </categories>
        </payload>
      </value>
    </dbRecord>
    <dbRecord>
      <key>
        ::namespace3::file2.h.1
      </key>
      <value>
        <name>
          Himanshu
        </name>
        <description>
          file2.h file
        </description>
        <children>
        </children>
        <payload>
          <value>
            ../root/namespace3/file2.h.1
          </value>
          <namespace>
            ::namespace3::
          </namespace>
          <status>
            2
          </status>
          <categories>
			  <category>
              Cat5
            </category>
            <category>
              Cat2
            </category>
          </categories>
        </payload>
      </value>
    </dbRecord>
	  <dbRecord>
      <key>
        ::namespace6::file4.cpp.1
      </key>
      <value>
        <name>
          Himanshu
        </name>
        <description>
          file4.cpp file
        </description>
        <children>
          <child>
            ::namespace6::file4.h.1
          </child>
		    <child>
            ::namespace1::namespace2::file1.cpp.1
          </child>
        </children>
        <payload>
          <value>
            ../root/namespace6/file4.cpp.1
          </value>
          <namespace>
            ::namespace6::
          </namespace>
          <status>
            0
          </status>
          <categories>
			  <category>
              Cat7
            </category>
          </categories>
        </payload>
      </value>
    </dbRecord>
    <dbRecord>
      <key>
        ::namespace6::file4.h.1
      </key>
      <value>
        <name>
          Himanshu
        </name>
        <description>
          file4.h file
        </description>
        <children>
        </children>
        <payload>
          <value>
            ../root/namespace6/file4.h.1
          </value>
          <namespace>
            ::namespace6::
          </namespace>
          <status>
            2
          </status>
          <categories>
			  <category>
              Cat10
            </category>
            <category>
              Cat2
            </category>
          </categories>
        </payload>
      </value>
    </dbRecord>
  </db>